mimul/__init__.py
mimul/main.py
mimul/mimul.py
mimul-1.0.1.dist-info/METADATA
mimul-1.0.1.dist-info/WHEEL
mimul-1.0.1.dist-info/entry_points.txt
mimul-1.0.1.dist-info/licenses/LICENSE
mimul-1.0.1.dist-info/RECORD
