Metadata-Version: 2.3
Name: mimul
Version: 1.0.1
Summary: A command-line interface tool to make a professional HTML website from MIML files.
Project-URL: Homepage, https://github.com/d3987ef8/mimul
Project-URL: Issues, https://github.com/d3987ef8/mimul/issues
Author-email: Jack Murray <info@jackmurray.com>
License-File: LICENSE
Classifier: License :: OSI Approved :: MIT License
Classifier: Operating System :: OS Independent
Classifier: Programming Language :: Python :: 3
Requires-Python: >=3.9
